{
  "input_symbols": [
    "AAPL",
    "MSFT"
  ],
  "n_input_obs": 4,
  "original_assets": [
    "AAPL",
    "MSFT"
  ],
  "dropped_assets": [],
  "n_obs_original": 4,
  "timestamp": 1763843408,
  "n_obs": 4,
  "n_assets": 2,
  "cond_XtX": 5.419570958119136,
  "used_ridge_lambda": 0.1,
  "eigenvalues": [
    -0.9836129522885002,
    0.3954449737975759
  ],
  "asset_order": [
    "AAPL",
    "MSFT"
  ],
  "persisted_paths": {
    "a_npy": "data\\processed\\var_outputs\\20251122T203008Z\\A_matrix.npy",
    "a_csv": "data\\processed\\var_outputs\\20251122T203008Z\\A_matrix.csv",
    "cov_npy": "data\\processed\\var_outputs\\20251122T203008Z\\cov_matrix.npy",
    "cov_csv": "data\\processed\\var_outputs\\20251122T203008Z\\cov_matrix.csv",
    "std_parquet": "data\\processed\\var_outputs\\20251122T203008Z\\standardized_returns.parquet",
    "diag_json": "data\\processed\\var_outputs\\20251122T203008Z\\diagnostics.json"
  }
}